evidentsource_core/__init__.py
evidentsource_core/protocols.py
evidentsource_core/py.typed
evidentsource_core/domain/__init__.py
evidentsource_core/domain/constraints.py
evidentsource_core/domain/errors.py
evidentsource_core/domain/events.py
evidentsource_core/domain/identifiers.py
evidentsource_core/domain/revision.py
evidentsource_core/domain/selectors.py
evidentsource_core/domain/state_change.py
evidentsource_core/domain/state_view.py
evidentsource_core-1.0.0rc1.dist-info/METADATA
evidentsource_core-1.0.0rc1.dist-info/WHEEL
evidentsource_core-1.0.0rc1.dist-info/RECORD
