Metadata-Version: 2.4
Name: evidentsource-core
Version: 1.0.0rc1
Summary: Core domain types for EvidentSource event sourcing platform
Project-URL: Documentation, https://docs.evidentstack.com/evidentsource
Project-URL: Repository, https://github.com/evidentsystems/evidentsource-sdks
Author-email: Evident Systems <hello@evidentsystems.com>
License-Expression: MIT OR Apache-2.0
Classifier: Development Status :: 4 - Beta
Classifier: Intended Audience :: Developers
Classifier: License :: OSI Approved :: Apache Software License
Classifier: License :: OSI Approved :: MIT License
Classifier: Programming Language :: Python :: 3
Classifier: Programming Language :: Python :: 3.12
Classifier: Programming Language :: Python :: 3.13
Classifier: Typing :: Typed
Requires-Python: >=3.12
Requires-Dist: attrs>=24.0.0
Requires-Dist: cattrs>=24.0.0
